flucoma/__init__.py
flucoma/core.py
flucoma/dataset.py
flucoma/exceptions.py
flucoma/fluid.py
flucoma/returns.py
flucoma/utils.py
python_flucoma-2.0.0.dist-info/LICENSE.txt
python_flucoma-2.0.0.dist-info/METADATA
python_flucoma-2.0.0.dist-info/WHEEL
python_flucoma-2.0.0.dist-info/top_level.txt
python_flucoma-2.0.0.dist-info/RECORD
