Metadata-Version: 2.1
Name: python-flucoma
Version: 2.0.0
Summary: Loose bindings to the FluCoMa command line
Home-page: https://github.com/jamesb93/python-flucoma
Author: James Bradbury
Author-email: hello@jamesbradbury.net
License: BSD
License-File: LICENSE.txt
Requires-Dist: SoundFile
Requires-Dist: numpy
Requires-Dist: scipy
